mssqlconnect/__init__.py
mssqlconnect/mssqlconnect.py
mssqlconnect-0.3.dist-info/LICENSE
mssqlconnect-0.3.dist-info/METADATA
mssqlconnect-0.3.dist-info/WHEEL
mssqlconnect-0.3.dist-info/top_level.txt
mssqlconnect-0.3.dist-info/RECORD
