Metadata-Version: 2.1
Name: mssqlconnect
Version: 0.3
Summary: mssqlconnect
Author: 棽杓
Author-email: 1047366140@qq,com
License: MIT
License-File: LICENSE
Requires-Dist: pymssql
